Metadata-Version: 2.1
Name: torchfunc-nightly
Version: 1658627601
Summary: PyTorch functions to improve performance, analyse models and make your life easier.
Home-page: https://github.com/szymonmaszke/torchfunc
Author: Szymon Maszke
Author-email: szymon.maszke@protonmail.com
License: MIT
Project-URL: Website, https://szymonmaszke.github.io/torchfunc
Project-URL: Documentation, https://szymonmaszke.github.io/torchfunc/#torchfunc
Project-URL: Issues, https://github.com/szymonmaszke/torchfunc/issues?q=is%3Aissue+is%3Aopen+sort%3Aupdated-desc
Keywords: pytorch torch functions performance visualize utils utilities recording
Platform: UNKNOWN
Classifier: Development Status :: 2 - Pre-Alpha
Classifier: Programming Language :: Python
Classifier: Programming Language :: Python :: 3
Classifier: Programming Language :: Python :: 3.6
Classifier: Programming Language :: Python :: 3.7
Classifier: Programming Language :: Python :: 3.8
Classifier: License :: OSI Approved :: MIT License
Classifier: Intended Audience :: Developers
Classifier: Operating System :: OS Independent
Classifier: Topic :: Scientific/Engineering
Classifier: Topic :: Software Development :: Libraries
Classifier: Topic :: Scientific/Engineering :: Artificial Intelligence
Classifier: Topic :: Software Development :: Libraries :: Python Modules
Requires-Python: >=3.6
Requires-Dist: torch (>=1.2.0)
